{
  "schema_version": "v1",
  "repos": {
    "yourear": {
      "open_issues": 0,
      "open_bugs": 0,
      "commits_6mo": 52,
      "stars": 1,
      "license": "MIT",
      "communityHealth": 85,
      "ciPassRate": 0.86,
      "vulns": {
        "count": 1,
        "critical": 0,
        "high": 0,
        "medium": 1,
        "low": 0,
        "max_severity": "medium"
      },
      "codeScanning": {
        "count": 0,
        "critical": 0,
        "high": 0,
        "medium": 0,
        "low": 0,
        "max_severity": null
      },
      "secretScanning": null,
      "ci": 5,
      "released_at": "2026-04-04T14:32:15Z",
      "pushed_at": "2026-04-29T13:24:46Z",
      "traffic": null,
      "computed": {
        "tier": "gold",
        "checks": [
          {
            "name": "Has CI workflows (2+)",
            "passed": true,
            "required_for": "gold"
          },
          {
            "name": "Has a license",
            "passed": true,
            "required_for": "silver"
          },
          {
            "name": "Fewer than 10 open bugs",
            "passed": true,
            "required_for": "gold"
          },
          {
            "name": "Release in the last 90 days",
            "passed": true,
            "required_for": "gold"
          },
          {
            "name": "Community health above 80%",
            "passed": true,
            "required_for": "gold"
          },
          {
            "name": "Security scanning configured",
            "passed": true,
            "required_for": "gold"
          },
          {
            "name": "Zero critical/high security findings",
            "passed": true,
            "required_for": "gold"
          },
          {
            "name": "Has CI workflows",
            "passed": true,
            "required_for": "silver"
          },
          {
            "name": "Community health above 50%",
            "passed": true,
            "required_for": "silver"
          },
          {
            "name": "Activity in the last 6 months",
            "passed": true,
            "required_for": "silver"
          },
          {
            "name": "Some activity (within 1 year)",
            "passed": true,
            "required_for": "bronze"
          }
        ],
        "next_step": null
      }
    },
    "sound3fy": {
      "open_issues": 0,
      "open_bugs": 0,
      "commits_6mo": 71,
      "stars": 3,
      "license": "MIT",
      "communityHealth": 100,
      "ciPassRate": 0.99,
      "vulns": {
        "count": 0,
        "critical": 0,
        "high": 0,
        "medium": 0,
        "low": 0,
        "max_severity": null
      },
      "codeScanning": {
        "count": 0,
        "critical": 0,
        "high": 0,
        "medium": 0,
        "low": 0,
        "max_severity": null
      },
      "secretScanning": null,
      "ci": 6,
      "released_at": "2025-12-20T09:59:52Z",
      "pushed_at": "2026-04-29T13:24:53Z",
      "traffic": null,
      "computed": {
        "tier": "gold",
        "checks": [
          {
            "name": "Has CI workflows (2+)",
            "passed": true,
            "required_for": "gold"
          },
          {
            "name": "Has a license",
            "passed": true,
            "required_for": "silver"
          },
          {
            "name": "Fewer than 10 open bugs",
            "passed": true,
            "required_for": "gold"
          },
          {
            "name": "Release in the last 90 days",
            "passed": true,
            "required_for": "gold"
          },
          {
            "name": "Community health above 80%",
            "passed": true,
            "required_for": "gold"
          },
          {
            "name": "Security scanning configured",
            "passed": true,
            "required_for": "gold"
          },
          {
            "name": "Zero critical/high security findings",
            "passed": true,
            "required_for": "gold"
          },
          {
            "name": "Has CI workflows",
            "passed": true,
            "required_for": "silver"
          },
          {
            "name": "Community health above 50%",
            "passed": true,
            "required_for": "silver"
          },
          {
            "name": "Activity in the last 6 months",
            "passed": true,
            "required_for": "silver"
          },
          {
            "name": "Some activity (within 1 year)",
            "passed": true,
            "required_for": "bronze"
          }
        ],
        "next_step": null
      }
    },
    "teams-for-linux": {
      "open_issues": 22,
      "open_bugs": 11,
      "commits_6mo": 367,
      "stars": 4638,
      "license": "GPL-3.0",
      "communityHealth": 85,
      "ciPassRate": 1,
      "vulns": {
        "count": 2,
        "critical": 0,
        "high": 0,
        "medium": 2,
        "low": 0,
        "max_severity": "medium"
      },
      "codeScanning": {
        "count": 0,
        "critical": 0,
        "high": 0,
        "medium": 0,
        "low": 0,
        "max_severity": null
      },
      "secretScanning": {
        "count": 0
      },
      "ci": 15,
      "released_at": "2026-04-24T14:54:11Z",
      "pushed_at": "2026-04-28T19:20:04Z",
      "traffic": null,
      "computed": {
        "tier": "silver",
        "checks": [
          {
            "name": "Has CI workflows (2+)",
            "passed": true,
            "required_for": "gold"
          },
          {
            "name": "Has a license",
            "passed": true,
            "required_for": "silver"
          },
          {
            "name": "Fewer than 10 open bugs",
            "passed": false,
            "required_for": "gold"
          },
          {
            "name": "Release in the last 90 days",
            "passed": true,
            "required_for": "gold"
          },
          {
            "name": "Community health above 80%",
            "passed": true,
            "required_for": "gold"
          },
          {
            "name": "Security scanning configured",
            "passed": true,
            "required_for": "gold"
          },
          {
            "name": "Zero critical/high security findings",
            "passed": true,
            "required_for": "gold"
          },
          {
            "name": "Has CI workflows",
            "passed": true,
            "required_for": "silver"
          },
          {
            "name": "Community health above 50%",
            "passed": true,
            "required_for": "silver"
          },
          {
            "name": "Activity in the last 6 months",
            "passed": true,
            "required_for": "silver"
          },
          {
            "name": "Some activity (within 1 year)",
            "passed": true,
            "required_for": "bronze"
          }
        ],
        "next_step": "Fewer than 10 open bugs"
      }
    },
    "ismaelmartinez.me.uk": {
      "open_issues": 1,
      "open_bugs": 0,
      "commits_6mo": 90,
      "stars": 1,
      "license": "MIT",
      "communityHealth": 85,
      "ciPassRate": 0.9,
      "vulns": {
        "count": 1,
        "critical": 0,
        "high": 0,
        "medium": 1,
        "low": 0,
        "max_severity": "medium"
      },
      "codeScanning": {
        "count": 0,
        "critical": 0,
        "high": 0,
        "medium": 0,
        "low": 0,
        "max_severity": null
      },
      "secretScanning": {
        "count": 0
      },
      "ci": 7,
      "released_at": "2026-04-04T14:32:15Z",
      "pushed_at": "2026-04-29T13:24:59Z",
      "traffic": null,
      "computed": {
        "tier": "gold",
        "checks": [
          {
            "name": "Has CI workflows (2+)",
            "passed": true,
            "required_for": "gold"
          },
          {
            "name": "Has a license",
            "passed": true,
            "required_for": "silver"
          },
          {
            "name": "Fewer than 10 open bugs",
            "passed": true,
            "required_for": "gold"
          },
          {
            "name": "Release in the last 90 days",
            "passed": true,
            "required_for": "gold"
          },
          {
            "name": "Community health above 80%",
            "passed": true,
            "required_for": "gold"
          },
          {
            "name": "Security scanning configured",
            "passed": true,
            "required_for": "gold"
          },
          {
            "name": "Zero critical/high security findings",
            "passed": true,
            "required_for": "gold"
          },
          {
            "name": "Has CI workflows",
            "passed": true,
            "required_for": "silver"
          },
          {
            "name": "Community health above 50%",
            "passed": true,
            "required_for": "silver"
          },
          {
            "name": "Activity in the last 6 months",
            "passed": true,
            "required_for": "silver"
          },
          {
            "name": "Some activity (within 1 year)",
            "passed": true,
            "required_for": "bronze"
          }
        ],
        "next_step": null
      }
    },
    "generator-atlassian-compass-event-catalog": {
      "open_issues": 0,
      "open_bugs": 0,
      "commits_6mo": 183,
      "stars": 4,
      "license": "MIT",
      "communityHealth": 85,
      "ciPassRate": 0.989010989010989,
      "vulns": {
        "count": 0,
        "critical": 0,
        "high": 0,
        "medium": 0,
        "low": 0,
        "max_severity": null
      },
      "codeScanning": {
        "count": 0,
        "critical": 0,
        "high": 0,
        "medium": 0,
        "low": 0,
        "max_severity": null
      },
      "secretScanning": {
        "count": 0
      },
      "ci": 7,
      "released_at": "2026-04-20T20:38:19Z",
      "pushed_at": "2026-04-27T21:12:57Z",
      "traffic": null,
      "computed": {
        "tier": "gold",
        "checks": [
          {
            "name": "Has CI workflows (2+)",
            "passed": true,
            "required_for": "gold"
          },
          {
            "name": "Has a license",
            "passed": true,
            "required_for": "silver"
          },
          {
            "name": "Fewer than 10 open bugs",
            "passed": true,
            "required_for": "gold"
          },
          {
            "name": "Release in the last 90 days",
            "passed": true,
            "required_for": "gold"
          },
          {
            "name": "Community health above 80%",
            "passed": true,
            "required_for": "gold"
          },
          {
            "name": "Security scanning configured",
            "passed": true,
            "required_for": "gold"
          },
          {
            "name": "Zero critical/high security findings",
            "passed": true,
            "required_for": "gold"
          },
          {
            "name": "Has CI workflows",
            "passed": true,
            "required_for": "silver"
          },
          {
            "name": "Community health above 50%",
            "passed": true,
            "required_for": "silver"
          },
          {
            "name": "Activity in the last 6 months",
            "passed": true,
            "required_for": "silver"
          },
          {
            "name": "Some activity (within 1 year)",
            "passed": true,
            "required_for": "bronze"
          }
        ],
        "next_step": null
      }
    },
    "bonnie-wee-plot": {
      "open_issues": 0,
      "open_bugs": 0,
      "commits_6mo": 401,
      "stars": 1,
      "license": "NOASSERTION",
      "communityHealth": 85,
      "ciPassRate": 0.87,
      "vulns": {
        "count": 1,
        "critical": 0,
        "high": 0,
        "medium": 1,
        "low": 0,
        "max_severity": "medium"
      },
      "codeScanning": {
        "count": 0,
        "critical": 0,
        "high": 0,
        "medium": 0,
        "low": 0,
        "max_severity": null
      },
      "secretScanning": {
        "count": 0
      },
      "ci": 5,
      "released_at": "2026-04-04T14:32:15Z",
      "pushed_at": "2026-04-29T16:27:08Z",
      "traffic": null,
      "computed": {
        "tier": "gold",
        "checks": [
          {
            "name": "Has CI workflows (2+)",
            "passed": true,
            "required_for": "gold"
          },
          {
            "name": "Has a license",
            "passed": true,
            "required_for": "silver"
          },
          {
            "name": "Fewer than 10 open bugs",
            "passed": true,
            "required_for": "gold"
          },
          {
            "name": "Release in the last 90 days",
            "passed": true,
            "required_for": "gold"
          },
          {
            "name": "Community health above 80%",
            "passed": true,
            "required_for": "gold"
          },
          {
            "name": "Security scanning configured",
            "passed": true,
            "required_for": "gold"
          },
          {
            "name": "Zero critical/high security findings",
            "passed": true,
            "required_for": "gold"
          },
          {
            "name": "Has CI workflows",
            "passed": true,
            "required_for": "silver"
          },
          {
            "name": "Community health above 50%",
            "passed": true,
            "required_for": "silver"
          },
          {
            "name": "Activity in the last 6 months",
            "passed": true,
            "required_for": "silver"
          },
          {
            "name": "Some activity (within 1 year)",
            "passed": true,
            "required_for": "bronze"
          }
        ],
        "next_step": null
      }
    },
    "betis-escocia": {
      "open_issues": 0,
      "open_bugs": 0,
      "commits_6mo": 152,
      "stars": 1,
      "license": "MIT",
      "communityHealth": 85,
      "ciPassRate": 0.89,
      "vulns": {
        "count": 0,
        "critical": 0,
        "high": 0,
        "medium": 0,
        "low": 0,
        "max_severity": null
      },
      "codeScanning": {
        "count": 0,
        "critical": 0,
        "high": 0,
        "medium": 0,
        "low": 0,
        "max_severity": null
      },
      "secretScanning": {
        "count": 0
      },
      "ci": 6,
      "released_at": "2026-04-04T14:32:15Z",
      "pushed_at": "2026-04-27T08:15:41Z",
      "traffic": null,
      "computed": {
        "tier": "gold",
        "checks": [
          {
            "name": "Has CI workflows (2+)",
            "passed": true,
            "required_for": "gold"
          },
          {
            "name": "Has a license",
            "passed": true,
            "required_for": "silver"
          },
          {
            "name": "Fewer than 10 open bugs",
            "passed": true,
            "required_for": "gold"
          },
          {
            "name": "Release in the last 90 days",
            "passed": true,
            "required_for": "gold"
          },
          {
            "name": "Community health above 80%",
            "passed": true,
            "required_for": "gold"
          },
          {
            "name": "Security scanning configured",
            "passed": true,
            "required_for": "gold"
          },
          {
            "name": "Zero critical/high security findings",
            "passed": true,
            "required_for": "gold"
          },
          {
            "name": "Has CI workflows",
            "passed": true,
            "required_for": "silver"
          },
          {
            "name": "Community health above 50%",
            "passed": true,
            "required_for": "silver"
          },
          {
            "name": "Activity in the last 6 months",
            "passed": true,
            "required_for": "silver"
          },
          {
            "name": "Some activity (within 1 year)",
            "passed": true,
            "required_for": "bronze"
          }
        ],
        "next_step": null
      }
    },
    "ai-model-advisor": {
      "open_issues": 0,
      "open_bugs": 0,
      "commits_6mo": 170,
      "stars": 1,
      "license": "MIT",
      "communityHealth": 85,
      "ciPassRate": 0.87,
      "vulns": {
        "count": 0,
        "critical": 0,
        "high": 0,
        "medium": 0,
        "low": 0,
        "max_severity": null
      },
      "codeScanning": {
        "count": 0,
        "critical": 0,
        "high": 0,
        "medium": 0,
        "low": 0,
        "max_severity": null
      },
      "secretScanning": {
        "count": 0
      },
      "ci": 7,
      "released_at": "2026-04-04T14:32:15Z",
      "pushed_at": "2026-04-29T13:25:06Z",
      "traffic": null,
      "computed": {
        "tier": "gold",
        "checks": [
          {
            "name": "Has CI workflows (2+)",
            "passed": true,
            "required_for": "gold"
          },
          {
            "name": "Has a license",
            "passed": true,
            "required_for": "silver"
          },
          {
            "name": "Fewer than 10 open bugs",
            "passed": true,
            "required_for": "gold"
          },
          {
            "name": "Release in the last 90 days",
            "passed": true,
            "required_for": "gold"
          },
          {
            "name": "Community health above 80%",
            "passed": true,
            "required_for": "gold"
          },
          {
            "name": "Security scanning configured",
            "passed": true,
            "required_for": "gold"
          },
          {
            "name": "Zero critical/high security findings",
            "passed": true,
            "required_for": "gold"
          },
          {
            "name": "Has CI workflows",
            "passed": true,
            "required_for": "silver"
          },
          {
            "name": "Community health above 50%",
            "passed": true,
            "required_for": "silver"
          },
          {
            "name": "Activity in the last 6 months",
            "passed": true,
            "required_for": "silver"
          },
          {
            "name": "Some activity (within 1 year)",
            "passed": true,
            "required_for": "bronze"
          }
        ],
        "next_step": null
      }
    },
    "github-issue-triage-bot": {
      "open_issues": 2,
      "open_bugs": 0,
      "commits_6mo": 216,
      "stars": 1,
      "license": "MIT",
      "communityHealth": 100,
      "ciPassRate": 0.93,
      "vulns": {
        "count": 0,
        "critical": 0,
        "high": 0,
        "medium": 0,
        "low": 0,
        "max_severity": null
      },
      "codeScanning": {
        "count": 0,
        "critical": 0,
        "high": 0,
        "medium": 0,
        "low": 0,
        "max_severity": null
      },
      "secretScanning": {
        "count": 0
      },
      "ci": 11,
      "released_at": "2026-04-01T12:26:05Z",
      "pushed_at": "2026-04-29T13:25:41Z",
      "traffic": null,
      "computed": {
        "tier": "gold",
        "checks": [
          {
            "name": "Has CI workflows (2+)",
            "passed": true,
            "required_for": "gold"
          },
          {
            "name": "Has a license",
            "passed": true,
            "required_for": "silver"
          },
          {
            "name": "Fewer than 10 open bugs",
            "passed": true,
            "required_for": "gold"
          },
          {
            "name": "Release in the last 90 days",
            "passed": true,
            "required_for": "gold"
          },
          {
            "name": "Community health above 80%",
            "passed": true,
            "required_for": "gold"
          },
          {
            "name": "Security scanning configured",
            "passed": true,
            "required_for": "gold"
          },
          {
            "name": "Zero critical/high security findings",
            "passed": true,
            "required_for": "gold"
          },
          {
            "name": "Has CI workflows",
            "passed": true,
            "required_for": "silver"
          },
          {
            "name": "Community health above 50%",
            "passed": true,
            "required_for": "silver"
          },
          {
            "name": "Activity in the last 6 months",
            "passed": true,
            "required_for": "silver"
          },
          {
            "name": "Some activity (within 1 year)",
            "passed": true,
            "required_for": "bronze"
          }
        ],
        "next_step": null
      }
    },
    "repo-butler": {
      "open_issues": 0,
      "open_bugs": 0,
      "commits_6mo": 230,
      "stars": 3,
      "license": "MIT",
      "communityHealth": 85,
      "ciPassRate": 0.94,
      "vulns": {
        "count": 0,
        "critical": 0,
        "high": 0,
        "medium": 0,
        "low": 0,
        "max_severity": null
      },
      "codeScanning": {
        "count": 0,
        "critical": 0,
        "high": 0,
        "medium": 0,
        "low": 0,
        "max_severity": null
      },
      "secretScanning": {
        "count": 0
      },
      "ci": 7,
      "released_at": "2026-03-31T22:55:25Z",
      "pushed_at": "2026-04-29T13:25:36Z",
      "traffic": null,
      "computed": {
        "tier": "gold",
        "checks": [
          {
            "name": "Has CI workflows (2+)",
            "passed": true,
            "required_for": "gold"
          },
          {
            "name": "Has a license",
            "passed": true,
            "required_for": "silver"
          },
          {
            "name": "Fewer than 10 open bugs",
            "passed": true,
            "required_for": "gold"
          },
          {
            "name": "Release in the last 90 days",
            "passed": true,
            "required_for": "gold"
          },
          {
            "name": "Community health above 80%",
            "passed": true,
            "required_for": "gold"
          },
          {
            "name": "Security scanning configured",
            "passed": true,
            "required_for": "gold"
          },
          {
            "name": "Zero critical/high security findings",
            "passed": true,
            "required_for": "gold"
          },
          {
            "name": "Has CI workflows",
            "passed": true,
            "required_for": "silver"
          },
          {
            "name": "Community health above 50%",
            "passed": true,
            "required_for": "silver"
          },
          {
            "name": "Activity in the last 6 months",
            "passed": true,
            "required_for": "silver"
          },
          {
            "name": "Some activity (within 1 year)",
            "passed": true,
            "required_for": "bronze"
          }
        ],
        "next_step": null
      }
    },
    "wifisentinel": {
      "open_issues": 0,
      "open_bugs": 0,
      "commits_6mo": 226,
      "stars": 1,
      "license": "MIT",
      "communityHealth": 100,
      "ciPassRate": 0.8705882352941177,
      "vulns": {
        "count": 1,
        "critical": 0,
        "high": 0,
        "medium": 1,
        "low": 0,
        "max_severity": "medium"
      },
      "codeScanning": {
        "count": 0,
        "critical": 0,
        "high": 0,
        "medium": 0,
        "low": 0,
        "max_severity": null
      },
      "secretScanning": {
        "count": 0
      },
      "ci": 5,
      "released_at": "2026-04-01T08:19:52Z",
      "pushed_at": "2026-04-29T13:25:18Z",
      "traffic": null,
      "computed": {
        "tier": "gold",
        "checks": [
          {
            "name": "Has CI workflows (2+)",
            "passed": true,
            "required_for": "gold"
          },
          {
            "name": "Has a license",
            "passed": true,
            "required_for": "silver"
          },
          {
            "name": "Fewer than 10 open bugs",
            "passed": true,
            "required_for": "gold"
          },
          {
            "name": "Release in the last 90 days",
            "passed": true,
            "required_for": "gold"
          },
          {
            "name": "Community health above 80%",
            "passed": true,
            "required_for": "gold"
          },
          {
            "name": "Security scanning configured",
            "passed": true,
            "required_for": "gold"
          },
          {
            "name": "Zero critical/high security findings",
            "passed": true,
            "required_for": "gold"
          },
          {
            "name": "Has CI workflows",
            "passed": true,
            "required_for": "silver"
          },
          {
            "name": "Community health above 50%",
            "passed": true,
            "required_for": "silver"
          },
          {
            "name": "Activity in the last 6 months",
            "passed": true,
            "required_for": "silver"
          },
          {
            "name": "Some activity (within 1 year)",
            "passed": true,
            "required_for": "bronze"
          }
        ],
        "next_step": null
      }
    },
    "votescot": {
      "open_issues": 0,
      "open_bugs": 0,
      "commits_6mo": 198,
      "stars": 2,
      "license": "MIT",
      "communityHealth": 100,
      "ciPassRate": 0.94,
      "vulns": {
        "count": 0,
        "critical": 0,
        "high": 0,
        "medium": 0,
        "low": 0,
        "max_severity": null
      },
      "codeScanning": {
        "count": 0,
        "critical": 0,
        "high": 0,
        "medium": 0,
        "low": 0,
        "max_severity": null
      },
      "secretScanning": {
        "count": 0
      },
      "ci": 7,
      "released_at": "2026-04-05T23:25:44Z",
      "pushed_at": "2026-04-29T13:25:50Z",
      "traffic": null,
      "computed": {
        "tier": "gold",
        "checks": [
          {
            "name": "Has CI workflows (2+)",
            "passed": true,
            "required_for": "gold"
          },
          {
            "name": "Has a license",
            "passed": true,
            "required_for": "silver"
          },
          {
            "name": "Fewer than 10 open bugs",
            "passed": true,
            "required_for": "gold"
          },
          {
            "name": "Release in the last 90 days",
            "passed": true,
            "required_for": "gold"
          },
          {
            "name": "Community health above 80%",
            "passed": true,
            "required_for": "gold"
          },
          {
            "name": "Security scanning configured",
            "passed": true,
            "required_for": "gold"
          },
          {
            "name": "Zero critical/high security findings",
            "passed": true,
            "required_for": "gold"
          },
          {
            "name": "Has CI workflows",
            "passed": true,
            "required_for": "silver"
          },
          {
            "name": "Community health above 50%",
            "passed": true,
            "required_for": "silver"
          },
          {
            "name": "Activity in the last 6 months",
            "passed": true,
            "required_for": "silver"
          },
          {
            "name": "Some activity (within 1 year)",
            "passed": true,
            "required_for": "bronze"
          }
        ],
        "next_step": null
      }
    },
    "lounge-tv": {
      "open_issues": 0,
      "open_bugs": 0,
      "commits_6mo": 26,
      "stars": 0,
      "license": "MIT",
      "communityHealth": 85,
      "ciPassRate": 0.8636363636363636,
      "vulns": {
        "count": 0,
        "critical": 0,
        "high": 0,
        "medium": 0,
        "low": 0,
        "max_severity": null
      },
      "codeScanning": {
        "count": 0,
        "critical": 0,
        "high": 0,
        "medium": 0,
        "low": 0,
        "max_severity": null
      },
      "secretScanning": {
        "count": 0
      },
      "ci": 3,
      "released_at": "2026-04-07T07:04:50Z",
      "pushed_at": "2026-04-29T13:25:57Z",
      "traffic": null,
      "computed": {
        "tier": "gold",
        "checks": [
          {
            "name": "Has CI workflows (2+)",
            "passed": true,
            "required_for": "gold"
          },
          {
            "name": "Has a license",
            "passed": true,
            "required_for": "silver"
          },
          {
            "name": "Fewer than 10 open bugs",
            "passed": true,
            "required_for": "gold"
          },
          {
            "name": "Release in the last 90 days",
            "passed": true,
            "required_for": "gold"
          },
          {
            "name": "Community health above 80%",
            "passed": true,
            "required_for": "gold"
          },
          {
            "name": "Security scanning configured",
            "passed": true,
            "required_for": "gold"
          },
          {
            "name": "Zero critical/high security findings",
            "passed": true,
            "required_for": "gold"
          },
          {
            "name": "Has CI workflows",
            "passed": true,
            "required_for": "silver"
          },
          {
            "name": "Community health above 50%",
            "passed": true,
            "required_for": "silver"
          },
          {
            "name": "Activity in the last 6 months",
            "passed": true,
            "required_for": "silver"
          },
          {
            "name": "Some activity (within 1 year)",
            "passed": true,
            "required_for": "bronze"
          }
        ],
        "next_step": null
      }
    }
  }
}